tmllib/__init__.py
tmllib/aurora.py
tmllib/awstool.py
tmllib/bigquery.py
tmllib/bq_kintone.py
tmllib/config_abc.py
tmllib/elasticcache.py
tmllib/etltool.py
tmllib/evaluator.py
tmllib/kintone.py
tmllib/parallelget.py
tmllib-0.2.4.dist-info/licenses/LICENSE
tmllib-0.2.4.dist-info/METADATA
tmllib-0.2.4.dist-info/WHEEL
tmllib-0.2.4.dist-info/top_level.txt
tmllib-0.2.4.dist-info/RECORD
