Metadata-Version: 2.4
Name: tmllib
Version: 0.2.4
Summary: etl tools for machine leraning.
Home-page: https://github.com/takemi-ohama/tmllib
Author: Takemi Ohama
Author-email: takmei.ohama@gmail.com
License: MIT
Keywords: etl,machine learning,bigquery,kintone
Classifier: Development Status :: 1 - Planning
Classifier: License :: OSI Approved :: MIT License
Classifier: Programming Language :: Python
Classifier: Programming Language :: Python :: 3
Classifier: Programming Language :: Python :: 3.10
Classifier: Programming Language :: Python :: 3.11
Classifier: Topic :: Database
Classifier: Topic :: Software Development :: Libraries :: Python Modules
License-File: LICENSE
Requires-Dist: pandas
Requires-Dist: sqlalchemy
Requires-Dist: boto3
Requires-Dist: google.cloud
Requires-Dist: pydantic
Requires-Dist: setuptools
Requires-Dist: scikit-learn
Requires-Dist: redis
Dynamic: author
Dynamic: author-email
Dynamic: classifier
Dynamic: description
Dynamic: home-page
Dynamic: keywords
Dynamic: license
Dynamic: license-file
Dynamic: requires-dist
Dynamic: summary
